anam_mcp/__init__.py
anam_mcp/client.py
anam_mcp/recall.py
anam_mcp/server.py
anam_mcp-0.1.13.dist-info/METADATA
anam_mcp-0.1.13.dist-info/WHEEL
anam_mcp-0.1.13.dist-info/entry_points.txt
anam_mcp-0.1.13.dist-info/licenses/LICENSE
anam_mcp-0.1.13.dist-info/RECORD
