Metadata-Version: 2.4
Name: anam-mcp
Version: 0.1.13
Summary: Official Anam AI MCP server for managing AI personas
Project-URL: Homepage, https://github.com/anam-org/anam-mcp
Project-URL: Documentation, https://docs.anam.ai
Project-URL: Repository, https://github.com/anam-org/anam-mcp
Project-URL: Issues, https://github.com/anam-org/anam-mcp/issues
Author-email: Anam AI <support@anam.ai>
License-Expression: MIT
License-File: LICENSE
Keywords: ai,anam,avatar,digital-human,mcp,persona
Classifier: Development Status :: 4 - Beta
Classifier: Intended Audience :: Developers
Classifier: License :: OSI Approved :: MIT License
Classifier: Programming Language :: Python :: 3
Classifier: Programming Language :: Python :: 3.10
Classifier: Programming Language :: Python :: 3.11
Classifier: Programming Language :: Python :: 3.12
Requires-Python: >=3.10
Requires-Dist: httpx>=0.27.0
Requires-Dist: mcp>=1.0.0
Requires-Dist: pydantic>=2.0.0
Provides-Extra: dev
Requires-Dist: pytest-asyncio>=0.23.0; extra == 'dev'
Requires-Dist: pytest>=8.0.0; extra == 'dev'
